AUTHORS.rst
CONTRIBUTING.rst
HISTORY.rst
LICENSE
MANIFEST.in
README.rst
setup.cfg
setup.py
docs/Makefile
docs/authors.rst
docs/conf.py
docs/contributing.rst
docs/history.rst
docs/index.rst
docs/installation.rst
docs/make.bat
docs/readme.rst
docs/usage.rst
docs/modules/bigquery.rst
docs/modules/compute.rst
docs/modules/dataproc.rst
docs/modules/drive.rst
docs/modules/gmail.rst
docs/modules/storage.rst
docs/modules/utils.rst
gwrappy/__init__.py
gwrappy/errors.py
gwrappy/scopes.py
gwrappy/service.py
gwrappy/utils.py
gwrappy.egg-info/PKG-INFO
gwrappy.egg-info/SOURCES.txt
gwrappy.egg-info/dependency_links.txt
gwrappy.egg-info/not-zip-safe
gwrappy.egg-info/requires.txt
gwrappy.egg-info/top_level.txt
gwrappy/bigquery/__init__.py
gwrappy/bigquery/bigquery.py
gwrappy/bigquery/errors.py
gwrappy/bigquery/utils.py
gwrappy/compute/__init__.py
gwrappy/compute/compute.py
gwrappy/dataproc/__init__.py
gwrappy/dataproc/dataproc.py
gwrappy/dataproc/utils.py
gwrappy/drive/__init__.py
gwrappy/drive/drive.py
gwrappy/drive/utils.py
gwrappy/gmail/__init__.py
gwrappy/gmail/gmail.py
gwrappy/gmail/utils.py
gwrappy/storage/__init__.py
gwrappy/storage/storage.py
gwrappy/storage/utils.py