Metadata-Version: 1.1
Name: gwrappy
Version: 0.4.1
Summary: User friendly wrapper for Google APIs
Home-page: https://github.com/danielpoonwj/gwrappy
Author: Daniel Poon
Author-email: daniel.poon.wenjie@gmail.com
License: Apache Software License 2.0
Keywords: google,cloud,gcloud
Platform: UNKNOWN
Classifier: Development Status :: 2 - Pre-Alpha
Classifier: Intended Audience :: Developers
Classifier: License :: OSI Approved :: Apache Software License
Classifier: Natural Language :: English
Classifier: Programming Language :: Python :: 2.7
Classifier: Programming Language :: Python :: 3.5
